pulumi_datarobot_utils/__init__.py
pulumi_datarobot_utils/_version.py
pulumi_datarobot_utils/py.typed
pulumi_datarobot_utils/common/__init__.py
pulumi_datarobot_utils/common/feature_flags.py
pulumi_datarobot_utils/common/urls.py
pulumi_datarobot_utils/pulumi/__init__.py
pulumi_datarobot_utils/pulumi/custom_model_deployment.py
pulumi_datarobot_utils/pulumi/playground_custom_model.py
pulumi_datarobot_utils/pulumi/proxy_llm_blueprint.py
pulumi_datarobot_utils/pulumi/rag_custom_model.py
pulumi_datarobot_utils/pulumi/stack.py
pulumi_datarobot_utils/schema/__init__.py
pulumi_datarobot_utils/schema/apps.py
pulumi_datarobot_utils/schema/base.py
pulumi_datarobot_utils/schema/common.py
pulumi_datarobot_utils/schema/custom_models.py
pulumi_datarobot_utils/schema/datasets.py
pulumi_datarobot_utils/schema/exec_envs.py
pulumi_datarobot_utils/schema/guardrails.py
pulumi_datarobot_utils/schema/llms.py
pulumi_datarobot_utils/schema/predictions.py
pulumi_datarobot_utils/schema/training.py
pulumi_datarobot_utils/schema/vectordb.py
pulumi_datarobot_utils-0.0.1.dist-info/METADATA
pulumi_datarobot_utils-0.0.1.dist-info/WHEEL
pulumi_datarobot_utils-0.0.1.dist-info/licenses/AUTHORS
pulumi_datarobot_utils-0.0.1.dist-info/licenses/LICENSE
pulumi_datarobot_utils-0.0.1.dist-info/RECORD
